setup.cfg
setup.py
cgp/__init__.py
cgp/__main__.py
cgp/cvodeint/__init__.py
cgp/cvodeint/core.py
cgp/cvodeint/example_ode.py
cgp/cvodeint/namedcvodeint.py
cgp/cvodeint/odeint.py
cgp/examples/__init__.py
cgp/examples/basic.py
cgp/examples/hpc.py
cgp/examples/noerror.py
cgp/examples/sensitivity.py
cgp/examples/sensitivity_beeler.py
cgp/examples/sigmoid.py
cgp/examples/simple.py
cgp/examples/simple_hdfcache.py
cgp/examples/simple_ipython_parallel.py
cgp/examples/simple_joblib.py
cgp/examples/test_nonexistent_folder_in_pythonpath.py
cgp/examples/sensitivity_service/__init__.py
cgp/examples/sensitivity_service/__main__.py
cgp/gt/__init__.py
cgp/gt/genotype.py
cgp/gt/gt2par.py
cgp/phenotyping/__init__.py
cgp/phenotyping/attractor.py
cgp/physmod/__init__.py
cgp/physmod/cellmlmodel.py
cgp/physmod/cythonize.py
cgp/sigmoidmodels/__init__.py
cgp/sigmoidmodels/doseresponse.py
cgp/sigmoidmodels/sigmoid_cvode.py
cgp/test/__init__.py
cgp/test/_test_clampable.py
cgp/test/test_arrayjob.py
cgp/test/test_attractor.py
cgp/test/test_cellmlmodel.py
cgp/test/test_clampable.py
cgp/test/test_cvodeint_core.py
cgp/test/test_elphys_analytic.py
cgp/test/test_elphys_examples.py
cgp/test/test_genotype.py
cgp/test/test_hdfcache.py
cgp/test/test_joblib.py
cgp/test/test_namedcvodeint.py
cgp/test/test_pickle.py
cgp/test/test_placevalue.py
cgp/test/test_poormanslock.py
cgp/test/test_rec2dict.py
cgp/test/test_recfun.py
cgp/test/test_unstruct.py
cgp/utils/__init__.py
cgp/utils/argrec.py
cgp/utils/arrayjob.py
cgp/utils/codegen.py
cgp/utils/commands.py
cgp/utils/dotdict.py
cgp/utils/extrema.py
cgp/utils/failwith.py
cgp/utils/flatten.py
cgp/utils/hdfcache.py
cgp/utils/load_memmap_offset.py
cgp/utils/numpy_hdf.py
cgp/utils/oat-ccd4f7c.py
cgp/utils/oat.bak.py
cgp/utils/ordereddict.py
cgp/utils/placevalue.py
cgp/utils/plot_directive_ggplot.py
cgp/utils/poormanslock.py
cgp/utils/qsubwrap.py
cgp/utils/qsubwrapmpi.py
cgp/utils/rec2dict.py
cgp/utils/recfun.py
cgp/utils/rnumpy.py
cgp/utils/splom.py
cgptoolbox.egg-info/PKG-INFO
cgptoolbox.egg-info/SOURCES.txt
cgptoolbox.egg-info/dependency_links.txt
cgptoolbox.egg-info/requires.txt
cgptoolbox.egg-info/top_level.txt