Metadata-Version: 1.0
Name: cgptoolbox
Version: 0.1.2
Summary: A toolbox for causally cohesive genotype-phenotype modeling
Home-page: http://arken.umb.no/~jonvi/cgptoolbox/
Author: Jon Olav Vik
Author-email: jonovik@gmail.com
License: UNKNOWN
Download-URL: https://github.com/jonovik/cgptoolbox
Platform: UNKNOWN
